alv/__init__.py
alv/alignment.py
alv/alignmentterminal.py
alv/colorize.py
alv/exceptions.py
alv/io.py
alv/version.py
alv-1.7.2.data/scripts/alv
tests/__init__.py
tests/test_alignment.py
tests/test_io.py
alv-1.7.2.dist-info/LICENSE
alv-1.7.2.dist-info/METADATA
alv-1.7.2.dist-info/WHEEL
alv-1.7.2.dist-info/top_level.txt
alv-1.7.2.dist-info/RECORD
