Metadata-Version: 2.1
Name: alv
Version: 1.7.2
Summary: A console-based sequence alignment viewer
Home-page: https://github.com/arvestad/alv
Author: Lars Arvestad
Author-email: arve@math.su.se
Classifier: Programming Language :: Python :: 3
Classifier: License :: OSI Approved :: GNU General Public License v3 (GPLv3)
Classifier: Operating System :: OS Independent
Classifier: Topic :: Scientific/Engineering :: Bio-Informatics
Requires-Python: >=3.5
License-File: LICENSE
Requires-Dist: biopython (>=1.70)
Requires-Dist: colorama (>=0.3.8)
